[
{
 "fields": {
  "gmms": [
   2,
   3,
   4,
   5,
   6,
   7,
   8,
   9,
   10,
   11,
   12,
   13,
   14,
   15,
   16,
   17,
   18,
   19,
   20,
   21,
   22,
   23,
   24,
   25,
   26,
   27,
   28,
   29,
   30,
   31,
   32,
   33,
   34,
   35,
   36,
   37,
   38,
   39,
   40,
   41,
   42,
   43,
   44,
   45,
   46,
   47,
   48,
   49,
   50,
   51,
   52,
   53,
   54,
   55,
   56,
   57,
   58,
   59,
   60,
   61,
   62,
   63,
   64,
   65,
   66,
   67,
   68,
   69,
   70,
   71,
   72,
   73,
   74,
   75,
   76,
   77,
   78,
   79,
   80,
   81,
   82,
   83,
   84
  ],
  "acronym": "",
  "updated_on": "2014-11-12T23:36:38.907Z",
  "type": "apoptosis",
  "name": "Apoptosis - Homo sapiens (human)",
  "created_on": "2014-11-12T23:36:38.907Z"
 },
 "model": "core.pathway",
 "pk": 1
},
{
 "fields": {
  "gmms": [
   6,
   7,
   13,
   66,
   67,
   68,
   69,
   85,
   86,
   87,
   88,
   89,
   90,
   91,
   92,
   93,
   94,
   95,
   96,
   97,
   98,
   99,
   100,
   101,
   102,
   103,
   104,
   105,
   106,
   107,
   108,
   109,
   110,
   111,
   112,
   113,
   114,
   115,
   116,
   117,
   118,
   119,
   120,
   121,
   122,
   123,
   124,
   125,
   126,
   127,
   128
  ],
  "acronym": "",
  "updated_on": "2014-11-12T23:49:46.059Z",
  "type": "apoptosis",
  "name": "Apoptotic Execution Phase",
  "created_on": "2014-11-12T23:49:46.059Z"
 },
 "model": "core.pathway",
 "pk": 2
},
{
 "fields": {
  "gmms": [
   9,
   28,
   41,
   54,
   55,
   56,
   58,
   59,
   62,
   66,
   67,
   68
  ],
  "acronym": "",
  "updated_on": "2014-11-13T00:58:03.695Z",
  "type": "apoptosis",
  "name": "Apoptotic signaling in response to dna damage",
  "created_on": "2014-11-13T00:56:25.324Z"
 },
 "model": "core.pathway",
 "pk": 3
},
{
 "fields": {
  "approved_symbol": "AKT3",
  "active": true,
  "updated_on": "2014-11-12T23:39:53.034Z",
  "created_on": "2014-11-12T23:39:53.034Z"
 },
 "model": "core.gmm",
 "pk": 2
},
{
 "fields": {
  "approved_symbol": "IRAK3",
  "active": true,
  "updated_on": "2014-11-12T23:39:53.358Z",
  "created_on": "2014-11-12T23:39:53.358Z"
 },
 "model": "core.gmm",
 "pk": 3
},
{
 "fields": {
  "approved_symbol": "CHUK",
  "active": true,
  "updated_on": "2014-11-12T23:39:53.660Z",
  "created_on": "2014-11-12T23:39:53.660Z"
 },
 "model": "core.gmm",
 "pk": 4
},
{
 "fields": {
  "approved_symbol": "CSF2RB",
  "active": true,
  "updated_on": "2014-11-12T23:39:53.950Z",
  "created_on": "2014-11-12T23:39:53.950Z"
 },
 "model": "core.gmm",
 "pk": 5
},
{
 "fields": {
  "approved_symbol": "DFFA",
  "active": true,
  "updated_on": "2014-11-12T23:39:54.241Z",
  "created_on": "2014-11-12T23:39:54.240Z"
 },
 "model": "core.gmm",
 "pk": 6
},
{
 "fields": {
  "approved_symbol": "DFFB",
  "active": true,
  "updated_on": "2014-11-12T23:39:54.541Z",
  "created_on": "2014-11-12T23:39:54.541Z"
 },
 "model": "core.gmm",
 "pk": 7
},
{
 "fields": {
  "approved_symbol": "ENDOG",
  "active": true,
  "updated_on": "2014-11-12T23:39:54.831Z",
  "created_on": "2014-11-12T23:39:54.831Z"
 },
 "model": "core.gmm",
 "pk": 8
},
{
 "fields": {
  "approved_symbol": "AKT1",
  "active": true,
  "updated_on": "2014-11-12T23:39:55.112Z",
  "created_on": "2014-11-12T23:39:55.112Z"
 },
 "model": "core.gmm",
 "pk": 9
},
{
 "fields": {
  "approved_symbol": "AKT2",
  "active": true,
  "updated_on": "2014-11-12T23:39:55.415Z",
  "created_on": "2014-11-12T23:39:55.414Z"
 },
 "model": "core.gmm",
 "pk": 10
},
{
 "fields": {
  "approved_symbol": "PIK3R5",
  "active": true,
  "updated_on": "2014-11-12T23:39:55.727Z",
  "created_on": "2014-11-12T23:39:55.727Z"
 },
 "model": "core.gmm",
 "pk": 11
},
{
 "fields": {
  "approved_symbol": "APAF1",
  "active": true,
  "updated_on": "2014-11-12T23:39:56.051Z",
  "created_on": "2014-11-12T23:39:56.050Z"
 },
 "model": "core.gmm",
 "pk": 12
},
{
 "fields": {
  "approved_symbol": "BIRC2",
  "active": true,
  "updated_on": "2014-11-12T23:39:56.386Z",
  "created_on": "2014-11-12T23:39:56.386Z"
 },
 "model": "core.gmm",
 "pk": 13
},
{
 "fields": {
  "approved_symbol": "BIRC3",
  "active": true,
  "updated_on": "2014-11-12T23:39:56.665Z",
  "created_on": "2014-11-12T23:39:56.665Z"
 },
 "model": "core.gmm",
 "pk": 14
},
{
 "fields": {
  "approved_symbol": "XIAP",
  "active": true,
  "updated_on": "2014-11-12T23:39:57.011Z",
  "created_on": "2014-11-12T23:39:57.011Z"
 },
 "model": "core.gmm",
 "pk": 15
},
{
 "fields": {
  "approved_symbol": "FAS",
  "active": true,
  "updated_on": "2014-11-12T23:39:57.369Z",
  "created_on": "2014-11-12T23:39:57.368Z"
 },
 "model": "core.gmm",
 "pk": 16
},
{
 "fields": {
  "approved_symbol": "IKBKB",
  "active": true,
  "updated_on": "2014-11-12T23:39:57.759Z",
  "created_on": "2014-11-12T23:39:57.759Z"
 },
 "model": "core.gmm",
 "pk": 17
},
{
 "fields": {
  "approved_symbol": "IL1A",
  "active": true,
  "updated_on": "2014-11-12T23:39:58.117Z",
  "created_on": "2014-11-12T23:39:58.117Z"
 },
 "model": "core.gmm",
 "pk": 18
},
{
 "fields": {
  "approved_symbol": "IL1B",
  "active": true,
  "updated_on": "2014-11-12T23:39:58.418Z",
  "created_on": "2014-11-12T23:39:58.418Z"
 },
 "model": "core.gmm",
 "pk": 19
},
{
 "fields": {
  "approved_symbol": "IL1R1",
  "active": true,
  "updated_on": "2014-11-12T23:39:58.742Z",
  "created_on": "2014-11-12T23:39:58.742Z"
 },
 "model": "core.gmm",
 "pk": 20
},
{
 "fields": {
  "approved_symbol": "IL1RAP",
  "active": true,
  "updated_on": "2014-11-12T23:39:59.065Z",
  "created_on": "2014-11-12T23:39:59.065Z"
 },
 "model": "core.gmm",
 "pk": 21
},
{
 "fields": {
  "approved_symbol": "FASLG",
  "active": true,
  "updated_on": "2014-11-12T23:39:59.367Z",
  "created_on": "2014-11-12T23:39:59.367Z"
 },
 "model": "core.gmm",
 "pk": 22
},
{
 "fields": {
  "approved_symbol": "IL3",
  "active": true,
  "updated_on": "2014-11-12T23:39:59.691Z",
  "created_on": "2014-11-12T23:39:59.691Z"
 },
 "model": "core.gmm",
 "pk": 23
},
{
 "fields": {
  "approved_symbol": "IL3RA",
  "active": true,
  "updated_on": "2014-11-12T23:40:00.016Z",
  "created_on": "2014-11-12T23:40:00.016Z"
 },
 "model": "core.gmm",
 "pk": 24
},
{
 "fields": {
  "approved_symbol": "IRAK1",
  "active": true,
  "updated_on": "2014-11-12T23:40:00.340Z",
  "created_on": "2014-11-12T23:40:00.340Z"
 },
 "model": "core.gmm",
 "pk": 25
},
{
 "fields": {
  "approved_symbol": "IRAK2",
  "active": true,
  "updated_on": "2014-11-12T23:40:00.642Z",
  "created_on": "2014-11-12T23:40:00.642Z"
 },
 "model": "core.gmm",
 "pk": 26
},
{
 "fields": {
  "approved_symbol": "MYD88",
  "active": true,
  "updated_on": "2014-11-12T23:40:00.954Z",
  "created_on": "2014-11-12T23:40:00.954Z"
 },
 "model": "core.gmm",
 "pk": 27
},
{
 "fields": {
  "approved_symbol": "ATM",
  "active": true,
  "updated_on": "2014-11-12T23:40:01.300Z",
  "created_on": "2014-11-12T23:40:01.300Z"
 },
 "model": "core.gmm",
 "pk": 28
},
{
 "fields": {
  "approved_symbol": "NFKB1",
  "active": true,
  "updated_on": "2014-11-12T23:40:01.612Z",
  "created_on": "2014-11-12T23:40:01.612Z"
 },
 "model": "core.gmm",
 "pk": 29
},
{
 "fields": {
  "approved_symbol": "NFKB2",
  "active": true,
  "updated_on": "2014-11-12T23:40:01.948Z",
  "created_on": "2014-11-12T23:40:01.948Z"
 },
 "model": "core.gmm",
 "pk": 30
},
{
 "fields": {
  "approved_symbol": "NFKBIA",
  "active": true,
  "updated_on": "2014-11-12T23:40:02.251Z",
  "created_on": "2014-11-12T23:40:02.250Z"
 },
 "model": "core.gmm",
 "pk": 31
},
{
 "fields": {
  "approved_symbol": "NGF",
  "active": true,
  "updated_on": "2014-11-12T23:40:02.574Z",
  "created_on": "2014-11-12T23:40:02.574Z"
 },
 "model": "core.gmm",
 "pk": 32
},
{
 "fields": {
  "approved_symbol": "NTRK1",
  "active": true,
  "updated_on": "2014-11-12T23:40:02.920Z",
  "created_on": "2014-11-12T23:40:02.920Z"
 },
 "model": "core.gmm",
 "pk": 33
},
{
 "fields": {
  "approved_symbol": "IRAK4",
  "active": true,
  "updated_on": "2014-11-12T23:40:03.299Z",
  "created_on": "2014-11-12T23:40:03.299Z"
 },
 "model": "core.gmm",
 "pk": 34
},
{
 "fields": {
  "approved_symbol": "PIK3CA",
  "active": true,
  "updated_on": "2014-11-12T23:40:03.668Z",
  "created_on": "2014-11-12T23:40:03.668Z"
 },
 "model": "core.gmm",
 "pk": 35
},
{
 "fields": {
  "approved_symbol": "PIK3CB",
  "active": true,
  "updated_on": "2014-11-12T23:40:04.025Z",
  "created_on": "2014-11-12T23:40:04.024Z"
 },
 "model": "core.gmm",
 "pk": 36
},
{
 "fields": {
  "approved_symbol": "PIK3CD",
  "active": true,
  "updated_on": "2014-11-12T23:40:04.381Z",
  "created_on": "2014-11-12T23:40:04.381Z"
 },
 "model": "core.gmm",
 "pk": 37
},
{
 "fields": {
  "approved_symbol": "PIK3CG",
  "active": true,
  "updated_on": "2014-11-12T23:40:04.719Z",
  "created_on": "2014-11-12T23:40:04.718Z"
 },
 "model": "core.gmm",
 "pk": 38
},
{
 "fields": {
  "approved_symbol": "PIK3R1",
  "active": true,
  "updated_on": "2014-11-12T23:40:05.042Z",
  "created_on": "2014-11-12T23:40:05.041Z"
 },
 "model": "core.gmm",
 "pk": 39
},
{
 "fields": {
  "approved_symbol": "PIK3R2",
  "active": true,
  "updated_on": "2014-11-12T23:40:05.366Z",
  "created_on": "2014-11-12T23:40:05.366Z"
 },
 "model": "core.gmm",
 "pk": 40
},
{
 "fields": {
  "approved_symbol": "CYCS",
  "active": true,
  "updated_on": "2014-11-12T23:40:05.667Z",
  "created_on": "2014-11-12T23:40:05.667Z"
 },
 "model": "core.gmm",
 "pk": 41
},
{
 "fields": {
  "approved_symbol": "PPP3CA",
  "active": true,
  "updated_on": "2014-11-12T23:40:06.002Z",
  "created_on": "2014-11-12T23:40:06.002Z"
 },
 "model": "core.gmm",
 "pk": 42
},
{
 "fields": {
  "approved_symbol": "PPP3CB",
  "active": true,
  "updated_on": "2014-11-12T23:40:06.337Z",
  "created_on": "2014-11-12T23:40:06.337Z"
 },
 "model": "core.gmm",
 "pk": 43
},
{
 "fields": {
  "approved_symbol": "PPP3CC",
  "active": true,
  "updated_on": "2014-11-12T23:40:06.639Z",
  "created_on": "2014-11-12T23:40:06.639Z"
 },
 "model": "core.gmm",
 "pk": 44
},
{
 "fields": {
  "approved_symbol": "PPP3R1",
  "active": true,
  "updated_on": "2014-11-12T23:40:06.942Z",
  "created_on": "2014-11-12T23:40:06.942Z"
 },
 "model": "core.gmm",
 "pk": 45
},
{
 "fields": {
  "approved_symbol": "PPP3R2",
  "active": true,
  "updated_on": "2014-11-12T23:40:07.276Z",
  "created_on": "2014-11-12T23:40:07.276Z"
 },
 "model": "core.gmm",
 "pk": 46
},
{
 "fields": {
  "approved_symbol": "PRKACA",
  "active": true,
  "updated_on": "2014-11-12T23:40:07.601Z",
  "created_on": "2014-11-12T23:40:07.600Z"
 },
 "model": "core.gmm",
 "pk": 47
},
{
 "fields": {
  "approved_symbol": "PRKACB",
  "active": true,
  "updated_on": "2014-11-12T23:40:07.913Z",
  "created_on": "2014-11-12T23:40:07.913Z"
 },
 "model": "core.gmm",
 "pk": 48
},
{
 "fields": {
  "approved_symbol": "PRKACG",
  "active": true,
  "updated_on": "2014-11-12T23:40:08.237Z",
  "created_on": "2014-11-12T23:40:08.237Z"
 },
 "model": "core.gmm",
 "pk": 49
},
{
 "fields": {
  "approved_symbol": "PRKAR1A",
  "active": true,
  "updated_on": "2014-11-12T23:40:08.539Z",
  "created_on": "2014-11-12T23:40:08.539Z"
 },
 "model": "core.gmm",
 "pk": 50
},
{
 "fields": {
  "approved_symbol": "PRKAR1B",
  "active": true,
  "updated_on": "2014-11-12T23:40:08.896Z",
  "created_on": "2014-11-12T23:40:08.896Z"
 },
 "model": "core.gmm",
 "pk": 51
},
{
 "fields": {
  "approved_symbol": "PRKAR2A",
  "active": true,
  "updated_on": "2014-11-12T23:40:09.289Z",
  "created_on": "2014-11-12T23:40:09.289Z"
 },
 "model": "core.gmm",
 "pk": 52
},
{
 "fields": {
  "approved_symbol": "PRKAR2B",
  "active": true,
  "updated_on": "2014-11-12T23:40:09.644Z",
  "created_on": "2014-11-12T23:40:09.644Z"
 },
 "model": "core.gmm",
 "pk": 53
},
{
 "fields": {
  "approved_symbol": "BAD",
  "active": true,
  "updated_on": "2014-11-12T23:40:10.013Z",
  "created_on": "2014-11-12T23:40:10.013Z"
 },
 "model": "core.gmm",
 "pk": 54
},
{
 "fields": {
  "approved_symbol": "BAX",
  "active": true,
  "updated_on": "2014-11-12T23:40:10.459Z",
  "created_on": "2014-11-12T23:40:10.459Z"
 },
 "model": "core.gmm",
 "pk": 55
},
{
 "fields": {
  "approved_symbol": "BCL2",
  "active": true,
  "updated_on": "2014-11-12T23:40:10.827Z",
  "created_on": "2014-11-12T23:40:10.827Z"
 },
 "model": "core.gmm",
 "pk": 56
},
{
 "fields": {
  "approved_symbol": "RELA",
  "active": true,
  "updated_on": "2014-11-12T23:40:11.184Z",
  "created_on": "2014-11-12T23:40:11.184Z"
 },
 "model": "core.gmm",
 "pk": 57
},
{
 "fields": {
  "approved_symbol": "BCL2L1",
  "active": true,
  "updated_on": "2014-11-12T23:40:11.530Z",
  "created_on": "2014-11-12T23:40:11.530Z"
 },
 "model": "core.gmm",
 "pk": 58
},
{
 "fields": {
  "approved_symbol": "BID",
  "active": true,
  "updated_on": "2014-11-12T23:40:11.833Z",
  "created_on": "2014-11-12T23:40:11.833Z"
 },
 "model": "core.gmm",
 "pk": 59
},
{
 "fields": {
  "approved_symbol": "TNF",
  "active": true,
  "updated_on": "2014-11-12T23:40:12.146Z",
  "created_on": "2014-11-12T23:40:12.145Z"
 },
 "model": "core.gmm",
 "pk": 60
},
{
 "fields": {
  "approved_symbol": "TNFRSF1A",
  "active": true,
  "updated_on": "2014-11-12T23:40:12.459Z",
  "created_on": "2014-11-12T23:40:12.459Z"
 },
 "model": "core.gmm",
 "pk": 61
},
{
 "fields": {
  "approved_symbol": "TP53",
  "active": true,
  "updated_on": "2014-11-12T23:40:12.760Z",
  "created_on": "2014-11-12T23:40:12.760Z"
 },
 "model": "core.gmm",
 "pk": 62
},
{
 "fields": {
  "approved_symbol": "TRAF2",
  "active": true,
  "updated_on": "2014-11-12T23:40:13.139Z",
  "created_on": "2014-11-12T23:40:13.139Z"
 },
 "model": "core.gmm",
 "pk": 63
},
{
 "fields": {
  "approved_symbol": "CAPN1",
  "active": true,
  "updated_on": "2014-11-12T23:40:13.475Z",
  "created_on": "2014-11-12T23:40:13.475Z"
 },
 "model": "core.gmm",
 "pk": 64
},
{
 "fields": {
  "approved_symbol": "CAPN2",
  "active": true,
  "updated_on": "2014-11-12T23:40:13.821Z",
  "created_on": "2014-11-12T23:40:13.820Z"
 },
 "model": "core.gmm",
 "pk": 65
},
{
 "fields": {
  "approved_symbol": "CASP3",
  "active": true,
  "updated_on": "2014-11-12T23:40:14.290Z",
  "created_on": "2014-11-12T23:40:14.290Z"
 },
 "model": "core.gmm",
 "pk": 66
},
{
 "fields": {
  "approved_symbol": "CASP6",
  "active": true,
  "updated_on": "2014-11-12T23:40:14.725Z",
  "created_on": "2014-11-12T23:40:14.725Z"
 },
 "model": "core.gmm",
 "pk": 67
},
{
 "fields": {
  "approved_symbol": "CASP7",
  "active": true,
  "updated_on": "2014-11-12T23:40:15.049Z",
  "created_on": "2014-11-12T23:40:15.049Z"
 },
 "model": "core.gmm",
 "pk": 68
},
{
 "fields": {
  "approved_symbol": "CASP8",
  "active": true,
  "updated_on": "2014-11-12T23:40:15.362Z",
  "created_on": "2014-11-12T23:40:15.362Z"
 },
 "model": "core.gmm",
 "pk": 69
},
{
 "fields": {
  "approved_symbol": "CASP9",
  "active": true,
  "updated_on": "2014-11-12T23:40:15.675Z",
  "created_on": "2014-11-12T23:40:15.675Z"
 },
 "model": "core.gmm",
 "pk": 70
},
{
 "fields": {
  "approved_symbol": "CASP10",
  "active": true,
  "updated_on": "2014-11-12T23:40:15.975Z",
  "created_on": "2014-11-12T23:40:15.975Z"
 },
 "model": "core.gmm",
 "pk": 71
},
{
 "fields": {
  "approved_symbol": "PIK3R3",
  "active": true,
  "updated_on": "2014-11-12T23:40:16.422Z",
  "created_on": "2014-11-12T23:40:16.422Z"
 },
 "model": "core.gmm",
 "pk": 72
},
{
 "fields": {
  "approved_symbol": "IKBKG",
  "active": true,
  "updated_on": "2014-11-12T23:40:16.846Z",
  "created_on": "2014-11-12T23:40:16.846Z"
 },
 "model": "core.gmm",
 "pk": 73
},
{
 "fields": {
  "approved_symbol": "TRADD",
  "active": true,
  "updated_on": "2014-11-12T23:40:17.226Z",
  "created_on": "2014-11-12T23:40:17.226Z"
 },
 "model": "core.gmm",
 "pk": 74
},
{
 "fields": {
  "approved_symbol": "RIPK1",
  "active": true,
  "updated_on": "2014-11-12T23:40:17.528Z",
  "created_on": "2014-11-12T23:40:17.528Z"
 },
 "model": "core.gmm",
 "pk": 75
},
{
 "fields": {
  "approved_symbol": "TNFSF10",
  "active": true,
  "updated_on": "2014-11-12T23:40:17.862Z",
  "created_on": "2014-11-12T23:40:17.862Z"
 },
 "model": "core.gmm",
 "pk": 76
},
{
 "fields": {
  "approved_symbol": "FADD",
  "active": true,
  "updated_on": "2014-11-12T23:40:18.153Z",
  "created_on": "2014-11-12T23:40:18.153Z"
 },
 "model": "core.gmm",
 "pk": 77
},
{
 "fields": {
  "approved_symbol": "TNFRSF10D",
  "active": true,
  "updated_on": "2014-11-12T23:40:18.454Z",
  "created_on": "2014-11-12T23:40:18.453Z"
 },
 "model": "core.gmm",
 "pk": 78
},
{
 "fields": {
  "approved_symbol": "TNFRSF10C",
  "active": true,
  "updated_on": "2014-11-12T23:40:18.845Z",
  "created_on": "2014-11-12T23:40:18.845Z"
 },
 "model": "core.gmm",
 "pk": 79
},
{
 "fields": {
  "approved_symbol": "TNFRSF10B",
  "active": true,
  "updated_on": "2014-11-12T23:40:19.259Z",
  "created_on": "2014-11-12T23:40:19.259Z"
 },
 "model": "core.gmm",
 "pk": 80
},
{
 "fields": {
  "approved_symbol": "TNFRSF10A",
  "active": true,
  "updated_on": "2014-11-12T23:40:19.682Z",
  "created_on": "2014-11-12T23:40:19.682Z"
 },
 "model": "core.gmm",
 "pk": 81
},
{
 "fields": {
  "approved_symbol": "CFLAR",
  "active": true,
  "updated_on": "2014-11-12T23:40:19.983Z",
  "created_on": "2014-11-12T23:40:19.983Z"
 },
 "model": "core.gmm",
 "pk": 82
},
{
 "fields": {
  "approved_symbol": "MAP3K14",
  "active": true,
  "updated_on": "2014-11-12T23:40:20.275Z",
  "created_on": "2014-11-12T23:40:20.275Z"
 },
 "model": "core.gmm",
 "pk": 83
},
{
 "fields": {
  "approved_symbol": "AIFM1",
  "active": true,
  "updated_on": "2014-11-12T23:40:20.576Z",
  "created_on": "2014-11-12T23:40:20.576Z"
 },
 "model": "core.gmm",
 "pk": 84
},
{
 "fields": {
  "approved_symbol": "DNM1L",
  "active": true,
  "updated_on": "2014-11-12T23:51:29.133Z",
  "created_on": "2014-11-12T23:51:29.133Z"
 },
 "model": "core.gmm",
 "pk": 85
},
{
 "fields": {
  "approved_symbol": "BCAP31",
  "active": true,
  "updated_on": "2014-11-12T23:51:29.561Z",
  "created_on": "2014-11-12T23:51:29.561Z"
 },
 "model": "core.gmm",
 "pk": 86
},
{
 "fields": {
  "approved_symbol": "ADD1",
  "active": true,
  "updated_on": "2014-11-12T23:51:29.831Z",
  "created_on": "2014-11-12T23:51:29.831Z"
 },
 "model": "core.gmm",
 "pk": 87
},
{
 "fields": {
  "approved_symbol": "CTNNB1",
  "active": true,
  "updated_on": "2014-11-12T23:51:30.099Z",
  "created_on": "2014-11-12T23:51:30.099Z"
 },
 "model": "core.gmm",
 "pk": 88
},
{
 "fields": {
  "approved_symbol": "DSG1",
  "active": true,
  "updated_on": "2014-11-12T23:51:30.669Z",
  "created_on": "2014-11-12T23:51:30.669Z"
 },
 "model": "core.gmm",
 "pk": 89
},
{
 "fields": {
  "approved_symbol": "DSG2",
  "active": true,
  "updated_on": "2014-11-12T23:51:31.004Z",
  "created_on": "2014-11-12T23:51:31.003Z"
 },
 "model": "core.gmm",
 "pk": 90
},
{
 "fields": {
  "approved_symbol": "DSG3",
  "active": true,
  "updated_on": "2014-11-12T23:51:31.283Z",
  "created_on": "2014-11-12T23:51:31.283Z"
 },
 "model": "core.gmm",
 "pk": 91
},
{
 "fields": {
  "approved_symbol": "DSP",
  "active": true,
  "updated_on": "2014-11-12T23:51:31.607Z",
  "created_on": "2014-11-12T23:51:31.607Z"
 },
 "model": "core.gmm",
 "pk": 92
},
{
 "fields": {
  "approved_symbol": "ACIN1",
  "active": true,
  "updated_on": "2014-11-12T23:51:31.888Z",
  "created_on": "2014-11-12T23:51:31.888Z"
 },
 "model": "core.gmm",
 "pk": 93
},
{
 "fields": {
  "approved_symbol": "FNTA",
  "active": true,
  "updated_on": "2014-11-12T23:51:32.155Z",
  "created_on": "2014-11-12T23:51:32.155Z"
 },
 "model": "core.gmm",
 "pk": 94
},
{
 "fields": {
  "approved_symbol": "GAS2",
  "active": true,
  "updated_on": "2014-11-12T23:51:32.435Z",
  "created_on": "2014-11-12T23:51:32.435Z"
 },
 "model": "core.gmm",
 "pk": 95
},
{
 "fields": {
  "approved_symbol": "DBNL",
  "active": true,
  "updated_on": "2014-11-12T23:51:32.759Z",
  "created_on": "2014-11-12T23:51:32.759Z"
 },
 "model": "core.gmm",
 "pk": 96
},
{
 "fields": {
  "approved_symbol": "GSN",
  "active": true,
  "updated_on": "2014-11-12T23:51:33.082Z",
  "created_on": "2014-11-12T23:51:33.082Z"
 },
 "model": "core.gmm",
 "pk": 97
},
{
 "fields": {
  "approved_symbol": "H1F0",
  "active": true,
  "updated_on": "2014-11-12T23:51:33.362Z",
  "created_on": "2014-11-12T23:51:33.362Z"
 },
 "model": "core.gmm",
 "pk": 98
},
{
 "fields": {
  "approved_symbol": "HIST1H1C",
  "active": true,
  "updated_on": "2014-11-12T23:51:33.719Z",
  "created_on": "2014-11-12T23:51:33.719Z"
 },
 "model": "core.gmm",
 "pk": 99
},
{
 "fields": {
  "approved_symbol": "HIST1H1D",
  "active": true,
  "updated_on": "2014-11-12T23:51:34.111Z",
  "created_on": "2014-11-12T23:51:34.111Z"
 },
 "model": "core.gmm",
 "pk": 100
},
{
 "fields": {
  "approved_symbol": "HIST1H1E",
  "active": true,
  "updated_on": "2014-11-12T23:51:34.456Z",
  "created_on": "2014-11-12T23:51:34.456Z"
 },
 "model": "core.gmm",
 "pk": 101
},
{
 "fields": {
  "approved_symbol": "HIST1H1B",
  "active": true,
  "updated_on": "2014-11-12T23:51:34.769Z",
  "created_on": "2014-11-12T23:51:34.769Z"
 },
 "model": "core.gmm",
 "pk": 102
},
{
 "fields": {
  "approved_symbol": "HIST1H1A",
  "active": true,
  "updated_on": "2014-11-12T23:51:35.149Z",
  "created_on": "2014-11-12T23:51:35.149Z"
 },
 "model": "core.gmm",
 "pk": 103
},
{
 "fields": {
  "approved_symbol": "HMGB1",
  "active": true,
  "updated_on": "2014-11-12T23:51:35.450Z",
  "created_on": "2014-11-12T23:51:35.450Z"
 },
 "model": "core.gmm",
 "pk": 104
},
{
 "fields": {
  "approved_symbol": "HMGB2",
  "active": true,
  "updated_on": "2014-11-12T23:51:35.729Z",
  "created_on": "2014-11-12T23:51:35.729Z"
 },
 "model": "core.gmm",
 "pk": 105
},
{
 "fields": {
  "approved_symbol": "APC",
  "active": true,
  "updated_on": "2014-11-12T23:51:36.042Z",
  "created_on": "2014-11-12T23:51:36.042Z"
 },
 "model": "core.gmm",
 "pk": 106
},
{
 "fields": {
  "approved_symbol": "KPNA1",
  "active": true,
  "updated_on": "2014-11-12T23:51:36.457Z",
  "created_on": "2014-11-12T23:51:36.457Z"
 },
 "model": "core.gmm",
 "pk": 107
},
{
 "fields": {
  "approved_symbol": "KPNB1",
  "active": true,
  "updated_on": "2014-11-12T23:51:36.770Z",
  "created_on": "2014-11-12T23:51:36.769Z"
 },
 "model": "core.gmm",
 "pk": 108
},
{
 "fields": {
  "approved_symbol": "LMNA",
  "active": true,
  "updated_on": "2014-11-12T23:51:37.049Z",
  "created_on": "2014-11-12T23:51:37.049Z"
 },
 "model": "core.gmm",
 "pk": 109
},
{
 "fields": {
  "approved_symbol": "LMNB1",
  "active": true,
  "updated_on": "2014-11-12T23:51:37.351Z",
  "created_on": "2014-11-12T23:51:37.350Z"
 },
 "model": "core.gmm",
 "pk": 110
},
{
 "fields": {
  "approved_symbol": "MAPT",
  "active": true,
  "updated_on": "2014-11-12T23:51:37.719Z",
  "created_on": "2014-11-12T23:51:37.719Z"
 },
 "model": "core.gmm",
 "pk": 111
},
{
 "fields": {
  "approved_symbol": "OCLN",
  "active": true,
  "updated_on": "2014-11-12T23:51:38.054Z",
  "created_on": "2014-11-12T23:51:38.054Z"
 },
 "model": "core.gmm",
 "pk": 112
},
{
 "fields": {
  "approved_symbol": "PAK2",
  "active": true,
  "updated_on": "2014-11-12T23:51:38.489Z",
  "created_on": "2014-11-12T23:51:38.488Z"
 },
 "model": "core.gmm",
 "pk": 113
},
{
 "fields": {
  "approved_symbol": "PKP1",
  "active": true,
  "updated_on": "2014-11-12T23:51:38.814Z",
  "created_on": "2014-11-12T23:51:38.813Z"
 },
 "model": "core.gmm",
 "pk": 114
},
{
 "fields": {
  "approved_symbol": "PLEC1",
  "active": true,
  "updated_on": "2014-11-12T23:51:39.104Z",
  "created_on": "2014-11-12T23:51:39.104Z"
 },
 "model": "core.gmm",
 "pk": 115
},
{
 "fields": {
  "approved_symbol": "PRKCD",
  "active": true,
  "updated_on": "2014-11-12T23:51:39.539Z",
  "created_on": "2014-11-12T23:51:39.539Z"
 },
 "model": "core.gmm",
 "pk": 116
},
{
 "fields": {
  "approved_symbol": "PRKCQ",
  "active": true,
  "updated_on": "2014-11-12T23:51:39.896Z",
  "created_on": "2014-11-12T23:51:39.896Z"
 },
 "model": "core.gmm",
 "pk": 117
},
{
 "fields": {
  "approved_symbol": "PTK2",
  "active": true,
  "updated_on": "2014-11-12T23:51:40.231Z",
  "created_on": "2014-11-12T23:51:40.230Z"
 },
 "model": "core.gmm",
 "pk": 118
},
{
 "fields": {
  "approved_symbol": "ROCK1",
  "active": true,
  "updated_on": "2014-11-12T23:51:40.588Z",
  "created_on": "2014-11-12T23:51:40.588Z"
 },
 "model": "core.gmm",
 "pk": 119
},
{
 "fields": {
  "approved_symbol": "SATB1",
  "active": true,
  "updated_on": "2014-11-12T23:51:40.901Z",
  "created_on": "2014-11-12T23:51:40.901Z"
 },
 "model": "core.gmm",
 "pk": 120
},
{
 "fields": {
  "approved_symbol": "CLSPN",
  "active": true,
  "updated_on": "2014-11-12T23:51:41.204Z",
  "created_on": "2014-11-12T23:51:41.203Z"
 },
 "model": "core.gmm",
 "pk": 121
},
{
 "fields": {
  "approved_symbol": "BMX",
  "active": true,
  "updated_on": "2014-11-12T23:51:41.538Z",
  "created_on": "2014-11-12T23:51:41.538Z"
 },
 "model": "core.gmm",
 "pk": 122
},
{
 "fields": {
  "approved_symbol": "SPTAN1",
  "active": true,
  "updated_on": "2014-11-12T23:51:41.862Z",
  "created_on": "2014-11-12T23:51:41.862Z"
 },
 "model": "core.gmm",
 "pk": 123
},
{
 "fields": {
  "approved_symbol": "TJP1",
  "active": true,
  "updated_on": "2014-11-12T23:51:42.175Z",
  "created_on": "2014-11-12T23:51:42.175Z"
 },
 "model": "core.gmm",
 "pk": 124
},
{
 "fields": {
  "approved_symbol": "VIM",
  "active": true,
  "updated_on": "2014-11-12T23:51:42.531Z",
  "created_on": "2014-11-12T23:51:42.531Z"
 },
 "model": "core.gmm",
 "pk": 125
},
{
 "fields": {
  "approved_symbol": "STK24",
  "active": true,
  "updated_on": "2014-11-12T23:51:43.860Z",
  "created_on": "2014-11-12T23:51:43.860Z"
 },
 "model": "core.gmm",
 "pk": 126
},
{
 "fields": {
  "approved_symbol": "TJP2",
  "active": true,
  "updated_on": "2014-11-12T23:51:44.318Z",
  "created_on": "2014-11-12T23:51:44.318Z"
 },
 "model": "core.gmm",
 "pk": 127
},
{
 "fields": {
  "approved_symbol": "CDH1",
  "active": true,
  "updated_on": "2014-11-12T23:51:44.675Z",
  "created_on": "2014-11-12T23:51:44.675Z"
 },
 "model": "core.gmm",
 "pk": 128
}
]
